Samuranium/Config.py
Samuranium/ConfigUtils.py
Samuranium/DriverManager.py
Samuranium/Logger.py
Samuranium/Samuranium.py
Samuranium/WebElement.py
Samuranium/WebElements.py
Samuranium/__init__.py
Samuranium/exceptions/__init__.py
Samuranium/exceptions/selenium.py
Samuranium/utils/SelectorStrategies.py
Samuranium/utils/__init__.py
Samuranium/utils/classes.py
Samuranium/utils/general.py
Samuranium/utils/paths.py
Samuranium/utils/time.py
samuranium2-0.6.2.dist-info/LICENSE
samuranium2-0.6.2.dist-info/WHEEL
samuranium2-0.6.2.dist-info/METADATA
samuranium2-0.6.2.dist-info/RECORD
