Metadata-Version: 2.1
Name: samuranium2
Version: 0.6.2
Summary: Samuranium Automation Framework
Author: Alexis Giovoglanian (malazay)
Author-email: alexisgiovoglanian@southerncode.us
Requires-Python: >=3.6,<4.0
Classifier: Programming Language :: Python :: 3
Classifier: Programming Language :: Python :: 3.6
Classifier: Programming Language :: Python :: 3.7
Classifier: Programming Language :: Python :: 3.8
Classifier: Programming Language :: Python :: 3.9
Requires-Dist: configparser (>=5.0.2,<6.0.0)
Requires-Dist: selenium (>=3.141.0,<4.0.0)
Requires-Dist: webdriver-manager (>=3.4.2,<4.0.0)
